logging_rate_limiter/__init__.py
logging_rate_limiter/utils.py
tests/__init__.py
tests/conftest.py
tests/test_logging.py
logging_rate_limiter-0.0.1.dist-info/LICENSE
logging_rate_limiter-0.0.1.dist-info/METADATA
logging_rate_limiter-0.0.1.dist-info/WHEEL
logging_rate_limiter-0.0.1.dist-info/top_level.txt
logging_rate_limiter-0.0.1.dist-info/RECORD
