Metadata-Version: 2.1
Name: logging-rate-limiter
Version: 0.0.1
Summary: rate limiting filter for python logging module.
Home-page: https://github.com/jha-hitesh/logging-rate-limiter
Author: hitesh jha
Author-email: hitesh4official@gmail.com
Classifier: Programming Language :: Python :: 3
Classifier: Operating System :: OS Independent
Requires-Python: >=3.6
License-File: LICENSE
